sphinx_example_includer/__init__.py
sphinx_example_includer/__main__.py
sphinx_example_includer/common.py
sphinx_example_includer/includer.py
sphinx_example_includer/sphinxgen.py
sphinx_example_includer-0.6.dist-info/LICENSE
sphinx_example_includer-0.6.dist-info/METADATA
sphinx_example_includer-0.6.dist-info/WHEEL
sphinx_example_includer-0.6.dist-info/top_level.txt
sphinx_example_includer-0.6.dist-info/RECORD
