Metadata-Version: 2.1
Name: sphinx_example_includer
Version: 0.6
Summary: Include code examples to sphinx documentation
Author-email: Ahmad Alobaid <ahmad88me@gmail.com>
Project-URL: Homepage, https://github.com/ahmad88me/sphinx_example_includer
Project-URL: Issues, https://github.com/ahmad88me/sphinx_example_includer/issues
Classifier: Programming Language :: Python :: 3
Classifier: Operating System :: OS Independent
Classifier: Topic :: Documentation :: Sphinx
Classifier: Topic :: Documentation
Classifier: License :: OSI Approved :: Apache Software License
Requires-Python: >=3.8
License-File: LICENSE
Requires-Dist: tomli >=2.0.1
